{
  "language": "zh",
  "duration": 685.5691875,
  "segments": [
    {
      "start": 0.0,
      "end": 1.44,
      "text": "ARDC里面有哪些东西"
    },
    {
      "start": 1.44,
      "end": 3.12,
      "text": "咱们现在把它按着展开"
    },
    {
      "start": 3.12,
      "end": 5.24,
      "text": "咱们就直接拿一个星球里面回大的问题吧"
    },
    {
      "start": 5.24,
      "end": 6.56,
      "text": "说完理机箭时代引导来嘛"
    },
    {
      "start": 6.56,
      "end": 8.88,
      "text": "那么基于算理机箭全突铺就这一篇文章"
    },
    {
      "start": 8.88,
      "end": 11.68,
      "text": "这一段是驱动下的全路链梳理与机会点"
    },
    {
      "start": 11.68,
      "end": 12.24,
      "text": "这个呢"
    },
    {
      "start": 12.24,
      "end": 13.04,
      "text": "它就说完了"
    },
    {
      "start": 13.04,
      "end": 14.64,
      "text": "这一段是2.0后面有3.0"
    },
    {
      "start": 14.64,
      "end": 16.44,
      "text": "一不就是这个微似后面有R"
    },
    {
      "start": 16.44,
      "end": 17.36,
      "text": "还有什么支铺"
    },
    {
      "start": 17.36,
      "end": 19.4,
      "text": "minimark是一螺框的大模型对吧"
    },
    {
      "start": 19.4,
      "end": 21.44,
      "text": "就你先别说老美里面泡泡梦"
    },
    {
      "start": 21.44,
      "end": 23.04,
      "text": "我们这边是真的需要"
    },
    {
      "start": 23.04,
      "end": 24.68,
      "text": "所以说跳动大模型发布以后"
    },
    {
      "start": 24.68,
      "end": 26.24,
      "text": "你看它支持这个文字"
    },
    {
      "start": 26.24,
      "end": 26.88,
      "text": "图片"
    },
    {
      "start": 26.88,
      "end": 28.44,
      "text": "音频4.4摩坦书"
    },
    {
      "start": 28.44,
      "end": 29.4,
      "text": "就是复达运动场景"
    },
    {
      "start": 29.4,
      "end": 30.2,
      "text": "可用率一致"
    },
    {
      "start": 30.2,
      "end": 30.84,
      "text": "复理一致性"
    },
    {
      "start": 30.84,
      "end": 31.72,
      "text": "还有可控达"
    },
    {
      "start": 31.72,
      "end": 32.72,
      "text": "说它工业集派"
    },
    {
      "start": 32.72,
      "end": 33.76,
      "text": "就是电影之初了"
    },
    {
      "start": 33.76,
      "end": 35.24,
      "text": "那么这个大模型吃铺泡了"
    },
    {
      "start": 35.24,
      "end": 36.08,
      "text": "加上这个OpenS"
    },
    {
      "start": 36.08,
      "end": 36.56,
      "text": "什么说二"
    },
    {
      "start": 36.56,
      "end": 37.24,
      "text": "这个都不用说了"
    },
    {
      "start": 37.24,
      "end": 38.6,
      "text": "它彻底引爆了算理机口"
    },
    {
      "start": 38.6,
      "end": 40.72,
      "text": "那去年一个前沿的这个4.5摩坦"
    },
    {
      "start": 40.72,
      "end": 41.88,
      "text": "动作需要数万"
    },
    {
      "start": 41.88,
      "end": 43.2,
      "text": "还有数10万上的H100"
    },
    {
      "start": 43.2,
      "end": 44.84,
      "text": "B200等GDP等效算力"
    },
    {
      "start": 44.84,
      "end": 45.84,
      "text": "这个等效算力什么意思"
    },
    {
      "start": 45.84,
      "end": 48.92,
      "text": "就是说他们把这个G100和B200的算力卡"
    },
    {
      "start": 48.92,
      "end": 49.76,
      "text": "当成一个单位"
    },
    {
      "start": 49.76,
      "end": 50.84,
      "text": "比如说谷歌"
    },
    {
      "start": 50.84,
      "end": 51.88,
      "text": "大家的证明的TPO是谁"
    },
    {
      "start": 51.88,
      "end": 53.16,
      "text": "那大家就是在说"
    },
    {
      "start": 53.16,
      "end": 54.56,
      "text": "谷歌有多少TPO的时候"
    },
    {
      "start": 54.56,
      "end": 55.92,
      "text": "他不是说有多少"
    },
    {
      "start": 55.92,
      "end": 57.48,
      "text": "他自己的TPO的算力芯片"
    },
    {
      "start": 57.48,
      "end": 58.68,
      "text": "而说等效率他有多少"
    },
    {
      "start": 58.68,
      "end": 59.68,
      "text": "让H100的卡"
    },
    {
      "start": 59.68,
      "end": 61.28,
      "text": "H100的卡就等于一个算力单元嘛"
    },
    {
      "start": 61.28,
      "end": 61.88,
      "text": "对不对"
    },
    {
      "start": 61.88,
      "end": 63.4,
      "text": "那现在就说"
    },
    {
      "start": 63.4,
      "end": 65.24,
      "text": "我们国产也开始支持了"
    },
    {
      "start": 65.24,
      "end": 67.28,
      "text": "就是国产今年的那些芯片也要出货"
    },
    {
      "start": 67.28,
      "end": 68.76,
      "text": "AZ的平衡我跟不说是吧"
    },
    {
      "start": 68.76,
      "end": 70.2,
      "text": "当然那公司已经飞到天上去了"
    },
    {
      "start": 70.2,
      "end": 72.4,
      "text": "那么全球算力需求2025到2030年"
    },
    {
      "start": 72.4,
      "end": 73.68,
      "text": "就CGR预级"
    },
    {
      "start": 73.68,
      "end": 75.64,
      "text": "还要争上35%到50%"
    },
    {
      "start": 75.64,
      "end": 77.48,
      "text": "奉献变的制算2025年"
    },
    {
      "start": 77.48,
      "end": 78.48,
      "text": "已经达到了1000个"
    },
    {
      "start": 78.48,
      "end": 80.28,
      "text": "26年预级奔向1500家"
    },
    {
      "start": 80.28,
      "end": 82.44,
      "text": "东书七川八大书9家十大集群"
    },
    {
      "start": 82.44,
      "end": 83.12,
      "text": "家书落底"
    },
    {
      "start": 83.12,
      "end": 84.2,
      "text": "算力不再是硬件对解"
    },
    {
      "start": 84.2,
      "end": 85.4,
      "text": "而是芯片服务器"
    },
    {
      "start": 85.4,
      "end": 86.56,
      "text": "网络散热电源"
    },
    {
      "start": 86.56,
      "end": 89.44,
      "text": "数据中心人员的系统性基建工程"
    },
    {
      "start": 89.44,
      "end": 91.2,
      "text": "平静已经从这个芯片转向了"
    },
    {
      "start": 91.2,
      "end": 92.32,
      "text": "电力可用性"
    },
    {
      "start": 92.32,
      "end": 93.2,
      "text": "网络贷宽"
    },
    {
      "start": 93.2,
      "end": 93.92,
      "text": "散热效率"
    },
    {
      "start": 93.92,
      "end": 94.8,
      "text": "绿色可执性"
    },
    {
      "start": 94.8,
      "end": 97.24,
      "text": "这里我会把每一个我正规的重点"
    },
    {
      "start": 97.24,
      "end": 98.0,
      "text": "咱们绿色来"
    },
    {
      "start": 98.0,
      "end": 99.8,
      "text": "就是现在对咱们2026年"
    },
    {
      "start": 99.8,
      "end": 101.68,
      "text": "算是2027年都在这里面折腾了"
    },
    {
      "start": 101.68,
      "end": 103.88,
      "text": "你说AZ过时有没有其他的可替代象了"
    },
    {
      "start": 103.88,
      "end": 104.36,
      "text": "有"
    },
    {
      "start": 104.36,
      "end": 105.08,
      "text": "黄金"
    },
    {
      "start": 105.08,
      "end": 106.24,
      "text": "其他的我觉得没什么"
    },
    {
      "start": 106.24,
      "end": 107.32,
      "text": "太多的折腾空间了"
    },
    {
      "start": 107.32,
      "end": 109.0,
      "text": "就像那种这些都是好马"
    },
    {
      "start": 109.0,
      "end": 110.72,
      "text": "那它怎么分为算上人马"
    },
    {
      "start": 110.72,
      "end": 111.48,
      "text": "中上人马"
    },
    {
      "start": 111.48,
      "end": 112.48,
      "text": "中上马对不对"
    },
    {
      "start": 112.48,
      "end": 113.48,
      "text": "下的马是不算了"
    },
    {
      "start": 113.48,
      "end": 114.16,
      "text": "就是你要说"
    },
    {
      "start": 114.16,
      "end": 115.8,
      "text": "你渴望获得价值对不对"
    },
    {
      "start": 115.8,
      "end": 117.6,
      "text": "那你总要找一个协律最大的吧"
    },
    {
      "start": 117.6,
      "end": 118.8,
      "text": "是不是这个逻辑"
    },
    {
      "start": 118.8,
      "end": 119.92,
      "text": "基本上在你们心中说"
    },
    {
      "start": 119.92,
      "end": 121.16,
      "text": "协律这个才有猛吗对不对"
    },
    {
      "start": 121.16,
      "end": 121.96,
      "text": "你说它要过世"
    },
    {
      "start": 121.96,
      "end": 123.32,
      "text": "这些协律论分看能看"
    },
    {
      "start": 123.32,
      "end": 123.8,
      "text": "对吗"
    },
    {
      "start": 123.8,
      "end": 125.2,
      "text": "但我知道你们不是这种人"
    },
    {
      "start": 125.2,
      "end": 127.4,
      "text": "这个我希望你们打下这个念头对不对"
    },
    {
      "start": 127.4,
      "end": 128.16,
      "text": "来报科的时候"
    },
    {
      "start": 128.16,
      "end": 129.64,
      "text": "都说自己是价头对吧"
    },
    {
      "start": 129.64,
      "end": 131.64,
      "text": "那么下面是全面的结构为化的"
    },
    {
      "start": 131.64,
      "end": 132.52,
      "text": "性质的权链"
    },
    {
      "start": 132.52,
      "end": 133.44,
      "text": "基于2025年"
    },
    {
      "start": 133.44,
      "end": 134.96,
      "text": "风险率的算力产业团境图是"
    },
    {
      "start": 134.96,
      "end": 135.6,
      "text": "还有就是说"
    },
    {
      "start": 135.6,
      "end": 136.8,
      "text": "四十万产业链图股"
    },
    {
      "start": 136.8,
      "end": 138.96,
      "text": "还有AIDC报告以及全球区程和"
    },
    {
      "start": 138.96,
      "end": 140.84,
      "text": "就是分六大核心硬件塞到"
    },
    {
      "start": 140.84,
      "end": 142.0,
      "text": "以及三大托兰环节"
    },
    {
      "start": 142.0,
      "end": 143.84,
      "text": "每一个链路包括了核心内容"
    },
    {
      "start": 143.84,
      "end": 145.2,
      "text": "全球和风险率的关系公司"
    },
    {
      "start": 145.2,
      "end": 146.44,
      "text": "还有市场权力规模"
    },
    {
      "start": 146.44,
      "end": 147.36,
      "text": "还有2026"
    },
    {
      "start": 147.36,
      "end": 148.36,
      "text": "加爆发力有超级的"
    },
    {
      "start": 148.36,
      "end": 149.68,
      "text": "还有风险于学校典"
    },
    {
      "start": 149.68,
      "end": 150.08,
      "text": "第1个"
    },
    {
      "start": 150.08,
      "end": 151.56,
      "text": "六大核心硬件塞到了"
    },
    {
      "start": 151.56,
      "end": 154.4,
      "text": "就是在AIDC建设成本70%的80%的"
    },
    {
      "start": 154.4,
      "end": 156.12,
      "text": "这个一个就在AID芯片与半导体"
    },
    {
      "start": 156.12,
      "end": 157.12,
      "text": "这个是算力新到是吧"
    },
    {
      "start": 157.12,
      "end": 158.92,
      "text": "价值占比是40%到50%"
    },
    {
      "start": 158.92,
      "end": 160.32,
      "text": "那么核心内容就是GPU"
    },
    {
      "start": 160.32,
      "end": 160.96,
      "text": "ICC面"
    },
    {
      "start": 160.96,
      "end": 161.4,
      "text": "NPU"
    },
    {
      "start": 161.4,
      "end": 161.76,
      "text": "CPU"
    },
    {
      "start": 161.76,
      "end": 162.36,
      "text": "加速硬件"
    },
    {
      "start": 162.36,
      "end": 163.16,
      "text": "加接近资成"
    },
    {
      "start": 163.16,
      "end": 163.96,
      "text": "就其他底下"
    },
    {
      "start": 163.96,
      "end": 165.48,
      "text": "还有HBM内存风双"
    },
    {
      "start": 165.48,
      "end": 166.96,
      "text": "全球龙头肯定是十出略过"
    },
    {
      "start": 166.96,
      "end": 168.4,
      "text": "那么风险率的代表就是略过"
    },
    {
      "start": 168.4,
      "end": 169.68,
      "text": "然后就事实上潜力"
    },
    {
      "start": 169.68,
      "end": 172.68,
      "text": "全球AIDB2025年是921亿美元"
    },
    {
      "start": 172.68,
      "end": 174.28,
      "text": "你看老美里面不是支出6500亿"
    },
    {
      "start": 174.28,
      "end": 174.44,
      "text": "嘛"
    },
    {
      "start": 174.44,
      "end": 175.16,
      "text": "说了这几个公司"
    },
    {
      "start": 175.16,
      "end": 176.8,
      "text": "他们很多是拿去建电力消败的"
    },
    {
      "start": 176.8,
      "end": 178.12,
      "text": "那么风险率本土错量"
    },
    {
      "start": 178.12,
      "end": 179.68,
      "text": "2020年HV引炸20"
    },
    {
      "start": 179.68,
      "end": 180.6,
      "text": "那么2026年"
    },
    {
      "start": 180.6,
      "end": 182.84,
      "text": "国产化目要到30%到30%"
    },
    {
      "start": 182.84,
      "end": 183.6,
      "text": "爆发点"
    },
    {
      "start": 183.68,
      "end": 185.52,
      "text": "26年那个因为拿着Black whale"
    },
    {
      "start": 185.52,
      "end": 186.4,
      "text": "大规模量产"
    },
    {
      "start": 186.4,
      "end": 187.36,
      "text": "还有就是推理端"
    },
    {
      "start": 187.36,
      "end": 188.56,
      "text": "需求反超训练端"
    },
    {
      "start": 188.56,
      "end": 189.36,
      "text": "什么叫训练"
    },
    {
      "start": 189.36,
      "end": 190.24,
      "text": "现在训练大模型"
    },
    {
      "start": 190.24,
      "end": 190.72,
      "text": "就是说"
    },
    {
      "start": 190.72,
      "end": 191.6,
      "text": "比如说我最近出了一个"
    },
    {
      "start": 191.6,
      "end": 193.4,
      "text": "C但是2.0就是一个大模型"
    },
    {
      "start": 193.4,
      "end": 193.84,
      "text": "对吧"
    },
    {
      "start": 193.84,
      "end": 195.12,
      "text": "那么训练好了以后"
    },
    {
      "start": 195.12,
      "end": 196.2,
      "text": "他进入应用了以后"
    },
    {
      "start": 196.2,
      "end": 197.16,
      "text": "就是进入推理端了"
    },
    {
      "start": 197.16,
      "end": 197.92,
      "text": "就是开始用了"
    },
    {
      "start": 197.92,
      "end": 198.64,
      "text": "以前就像这一次"
    },
    {
      "start": 198.64,
      "end": 199.92,
      "text": "去研究火底料的配方"
    },
    {
      "start": 199.92,
      "end": 201.08,
      "text": "现在大规模的生产"
    },
    {
      "start": 201.08,
      "end": 202.28,
      "text": "这个火锅底料了"
    },
    {
      "start": 202.28,
      "end": 203.44,
      "text": "就开火锅工厂了"
    },
    {
      "start": 203.44,
      "end": 204.44,
      "text": "那么安静它多模太"
    },
    {
      "start": 204.44,
      "end": 205.2,
      "text": "还有比较"
    },
    {
      "start": 205.2,
      "end": 206.24,
      "text": "这种类似的驱动作"
    },
    {
      "start": 206.24,
      "end": 208.08,
      "text": "那么风烟运音制才倒鼻这个"
    },
    {
      "start": 208.08,
      "end": 209.96,
      "text": "确实H20画生成万卡几群"
    },
    {
      "start": 209.96,
      "end": 211.44,
      "text": "其实这个数字中心已经来投了"
    },
    {
      "start": 211.44,
      "end": 212.56,
      "text": "我说了说如果没有投"
    },
    {
      "start": 212.56,
      "end": 213.96,
      "text": "展过年是不可能生成那么多"
    },
    {
      "start": 213.96,
      "end": 214.84,
      "text": "谁但是是视频的"
    },
    {
      "start": 214.84,
      "end": 216.12,
      "text": "这个明确告诉各位"
    },
    {
      "start": 216.12,
      "end": 217.28,
      "text": "就大家能用的开心"
    },
    {
      "start": 217.28,
      "end": 218.88,
      "text": "虽然问题排队几个小时才能生成"
    },
    {
      "start": 218.88,
      "end": 220.88,
      "text": "但是如果没有这些算力中心"
    },
    {
      "start": 220.88,
      "end": 221.88,
      "text": "你肯定做不到视频了"
    },
    {
      "start": 221.88,
      "end": 222.72,
      "text": "你也不可能"
    },
    {
      "start": 222.72,
      "end": 224.04,
      "text": "往上失落你那边的破坊"
    },
    {
      "start": 224.04,
      "end": 225.88,
      "text": "就海光的DCU全面是配"
    },
    {
      "start": 225.88,
      "end": 227.68,
      "text": "LAMA,GMP,GNP,GNP,GNP,GNP,GNP,GNP,GNP"
    },
    {
      "start": 227.68,
      "end": 229.16,
      "text": "也就是他们在卖脱肯"
    },
    {
      "start": 229.16,
      "end": 230.44,
      "text": "然后我们交给这个"
    },
    {
      "start": 230.44,
      "end": 231.44,
      "text": "都包或者是GNP"
    },
    {
      "start": 231.44,
      "end": 232.4,
      "text": "又卖给海外"
    },
    {
      "start": 232.4,
      "end": 233.88,
      "text": "那么技能差距搜小的字"
    },
    {
      "start": 233.88,
      "end": 234.68,
      "text": "两到三倍以类"
    },
    {
      "start": 234.68,
      "end": 235.24,
      "text": "出发借"
    },
    {
      "start": 235.24,
      "end": 236.52,
      "text": "就大模型常链的推底"
    },
    {
      "start": 236.52,
      "end": 238.24,
      "text": "还有就是视频生成工业落地了"
    },
    {
      "start": 238.24,
      "end": 239.4,
      "text": "这个12万落地嘛 是吧"
    },
    {
      "start": 239.4,
      "end": 239.88,
      "text": "第二个"
    },
    {
      "start": 239.88,
      "end": 242.12,
      "text": "主线较AI的服务器比整机集成"
    },
    {
      "start": 242.12,
      "end": 244.24,
      "text": "这个虚感价值赞比20%至20%至30%"
    },
    {
      "start": 244.24,
      "end": 246.24,
      "text": "那核心内容就是GPU服务器"
    },
    {
      "start": 246.24,
      "end": 247.0,
      "text": "夜冷激贵"
    },
    {
      "start": 247.0,
      "end": 248.72,
      "text": "还有就是8卡16卡万卡基群"
    },
    {
      "start": 248.72,
      "end": 250.16,
      "text": "全球龙头有这个略过"
    },
    {
      "start": 250.16,
      "end": 251.2,
      "text": "风险略龙头跳过"
    },
    {
      "start": 251.2,
      "end": 251.92,
      "text": "那么事实上潜力"
    },
    {
      "start": 251.92,
      "end": 252.84,
      "text": "风险略的AI服务器"
    },
    {
      "start": 252.84,
      "end": 254.04,
      "text": "2025年超2000亿"
    },
    {
      "start": 254.04,
      "end": 256.12,
      "text": "全球AI服务器出货量26年翻倍"
    },
    {
      "start": 256.2,
      "end": 257.4,
      "text": "爆发的就是这个不太可谓"
    },
    {
      "start": 257.4,
      "end": 258.56,
      "text": "交付服务器就是"
    },
    {
      "start": 258.56,
      "end": 259.44,
      "text": "因为最新的穿力卡"
    },
    {
      "start": 259.44,
      "end": 260.72,
      "text": "还有就是风险略龙的巨头之外"
    },
    {
      "start": 260.72,
      "end": 261.44,
      "text": "内三家"
    },
    {
      "start": 261.44,
      "end": 262.52,
      "text": "那把资本开支大增"
    },
    {
      "start": 262.52,
      "end": 265.6,
      "text": "就光自己在26年就可能超1600亿同票子"
    },
    {
      "start": 265.6,
      "end": 266.44,
      "text": "用于这个AI"
    },
    {
      "start": 266.44,
      "end": 267.68,
      "text": "这车化机肯定是万卡"
    },
    {
      "start": 267.68,
      "end": 269.68,
      "text": "就是说白的要快速扩算力"
    },
    {
      "start": 269.68,
      "end": 271.48,
      "text": "这个里面我个人认为"
    },
    {
      "start": 271.48,
      "end": 272.48,
      "text": "最核心的还是夜冷"
    },
    {
      "start": 272.48,
      "end": 273.36,
      "text": "激贵的一些东西"
    },
    {
      "start": 273.36,
      "end": 275.56,
      "text": "说白了它含金的没有那么高"
    },
    {
      "start": 275.56,
      "end": 277.68,
      "text": "而夜冷的话龙头就不用扯了嘛"
    },
    {
      "start": 277.68,
      "end": 278.4,
      "text": "大家都知道"
    },
    {
      "start": 278.4,
      "end": 279.32,
      "text": "你说白了"
    },
    {
      "start": 279.32,
      "end": 281.4,
      "text": "你不想去研究了不多的时候"
    },
    {
      "start": 281.4,
      "end": 282.76,
      "text": "我真正的夜冷是钢区"
    },
    {
      "start": 282.76,
      "end": 284.32,
      "text": "现在的万卡很钢区"
    },
    {
      "start": 284.36,
      "end": 285.28,
      "text": "第三个 纯粹系统"
    },
    {
      "start": 285.28,
      "end": 286.32,
      "text": "就是这个HVM"
    },
    {
      "start": 286.32,
      "end": 286.88,
      "text": "还有DRIM"
    },
    {
      "start": 286.88,
      "end": 287.52,
      "text": "还有CSSD"
    },
    {
      "start": 287.52,
      "end": 288.04,
      "text": "燃热床"
    },
    {
      "start": 288.04,
      "end": 288.52,
      "text": "核心的东西"
    },
    {
      "start": 288.52,
      "end": 289.72,
      "text": "高宽大力纯的HVM"
    },
    {
      "start": 289.72,
      "end": 290.08,
      "text": "3E"
    },
    {
      "start": 290.08,
      "end": 290.8,
      "text": "HVM4"
    },
    {
      "start": 290.8,
      "end": 291.08,
      "text": "DRIM"
    },
    {
      "start": 291.08,
      "end": 292.0,
      "text": "还有SSD"
    },
    {
      "start": 292.0,
      "end": 292.8,
      "text": "那全球呢"
    },
    {
      "start": 292.8,
      "end": 293.28,
      "text": "掠过"
    },
    {
      "start": 293.28,
      "end": 293.84,
      "text": "然后呢"
    },
    {
      "start": 293.84,
      "end": 294.52,
      "text": "风险运动头"
    },
    {
      "start": 294.52,
      "end": 294.88,
      "text": "跳过"
    },
    {
      "start": 294.88,
      "end": 295.72,
      "text": "四上潜力了"
    },
    {
      "start": 295.72,
      "end": 296.88,
      "text": "全球纯粹"
    },
    {
      "start": 296.88,
      "end": 298.32,
      "text": "2025年是2600"
    },
    {
      "start": 298.32,
      "end": 299.28,
      "text": "33亿美刀"
    },
    {
      "start": 299.28,
      "end": 300.24,
      "text": "你看上面"
    },
    {
      "start": 300.24,
      "end": 301.48,
      "text": "风险运动的AI服务器"
    },
    {
      "start": 301.48,
      "end": 303.36,
      "text": "这个纯粹上面已经是多少钱了"
    },
    {
      "start": 303.36,
      "end": 304.52,
      "text": "接近2万亿的规模了"
    },
    {
      "start": 304.52,
      "end": 305.12,
      "text": "今年"
    },
    {
      "start": 305.12,
      "end": 305.92,
      "text": "按照这个节奏"
    },
    {
      "start": 305.92,
      "end": 307.04,
      "text": "不得3万亿4万亿"
    },
    {
      "start": 307.04,
      "end": 308.84,
      "text": "所以哈利是说他今年的利润"
    },
    {
      "start": 308.84,
      "end": 309.84,
      "text": "可能搞出1000亿美金"
    },
    {
      "start": 309.84,
      "end": 310.72,
      "text": "还是真有可能的"
    },
    {
      "start": 310.72,
      "end": 312.32,
      "text": "爆发点就是多摩太模型"
    },
    {
      "start": 312.32,
      "end": 313.88,
      "text": "需要喊亮的高宽在纯粹"
    },
    {
      "start": 313.88,
      "end": 315.48,
      "text": "HVM需求大利润"
    },
    {
      "start": 315.48,
      "end": 316.8,
      "text": "风险就不要说风险求了"
    },
    {
      "start": 316.8,
      "end": 318.96,
      "text": "是这个求远远大于共"
    },
    {
      "start": 318.96,
      "end": 320.4,
      "text": "他的确定应该是最强的"
    },
    {
      "start": 320.4,
      "end": 321.08,
      "text": "但是呢"
    },
    {
      "start": 321.08,
      "end": 322.0,
      "text": "因为我们这边"
    },
    {
      "start": 322.0,
      "end": 322.36,
      "text": "这么说"
    },
    {
      "start": 322.36,
      "end": 323.96,
      "text": "你有只能到较么就等那几个"
    },
    {
      "start": 323.96,
      "end": 325.32,
      "text": "人生产类存的上市"
    },
    {
      "start": 325.32,
      "end": 325.8,
      "text": "要么呢"
    },
    {
      "start": 325.8,
      "end": 326.32,
      "text": "你就直接"
    },
    {
      "start": 326.32,
      "end": 327.2,
      "text": "你在HVK看一看"
    },
    {
      "start": 327.2,
      "end": 328.04,
      "text": "总而来自这个东西"
    },
    {
      "start": 328.04,
      "end": 329.4,
      "text": "如果让我给纯粹打扶"
    },
    {
      "start": 329.4,
      "end": 330.0,
      "text": "吃娃娃"
    },
    {
      "start": 330.0,
      "end": 331.44,
      "text": "他的确定应比黄金还高"
    },
    {
      "start": 331.44,
      "end": 333.04,
      "text": "第四个就网络与顾连"
    },
    {
      "start": 333.04,
      "end": 334.52,
      "text": "郭摩坏交往基于童兰"
    },
    {
      "start": 334.52,
      "end": 335.08,
      "text": "曾经写的"
    },
    {
      "start": 335.08,
      "end": 336.36,
      "text": "今年我这么说嘛"
    },
    {
      "start": 336.36,
      "end": 337.32,
      "text": "这个系列大分之后"
    },
    {
      "start": 337.32,
      "end": 338.92,
      "text": "主任期全球龙都是略过"
    },
    {
      "start": 338.92,
      "end": 339.84,
      "text": "风险率挑过"
    },
    {
      "start": 339.84,
      "end": 340.48,
      "text": "然后这个东西"
    },
    {
      "start": 340.48,
      "end": 341.96,
      "text": "咱们就不用去多少了"
    },
    {
      "start": 341.96,
      "end": 342.76,
      "text": "你说来的"
    },
    {
      "start": 342.76,
      "end": 343.44,
      "text": "他不缺钱"
    },
    {
      "start": 343.44,
      "end": 343.96,
      "text": "他东西有"
    },
    {
      "start": 343.96,
      "end": 345.44,
      "text": "他不需要再在资本市场"
    },
    {
      "start": 345.44,
      "end": 346.36,
      "text": "证明他多牛逼"
    },
    {
      "start": 346.36,
      "end": 348.16,
      "text": "也不需要在技术上证明他多牛逼"
    },
    {
      "start": 348.16,
      "end": 349.72,
      "text": "老老实实做生意就行了"
    },
    {
      "start": 349.72,
      "end": 350.96,
      "text": "我们不会有一个什么"
    },
    {
      "start": 350.96,
      "end": 352.76,
      "text": "市值几万亿的郭摩坏公司出来的"
    },
    {
      "start": 352.76,
      "end": 353.8,
      "text": "下面第一梯队"
    },
    {
      "start": 353.8,
      "end": 354.24,
      "text": "打满"
    },
    {
      "start": 354.24,
      "end": 354.84,
      "text": "第二梯队"
    },
    {
      "start": 354.84,
      "end": 355.48,
      "text": "再列第三"
    },
    {
      "start": 355.48,
      "end": 355.56,
      "text": "第三"
    },
    {
      "start": 355.56,
      "end": 355.84,
      "text": "第梯队"
    },
    {
      "start": 355.84,
      "end": 356.76,
      "text": "还在找苗子"
    },
    {
      "start": 356.76,
      "end": 357.96,
      "text": "我跟你说个事就知道了"
    },
    {
      "start": 357.96,
      "end": 359.92,
      "text": "是不是有段时间反对平台经济"
    },
    {
      "start": 359.92,
      "end": 361.12,
      "text": "你还记得到这个事不"
    },
    {
      "start": 361.12,
      "end": 362.08,
      "text": "大概是五六年前"
    },
    {
      "start": 362.08,
      "end": 362.64,
      "text": "也就说"
    },
    {
      "start": 362.64,
      "end": 363.68,
      "text": "其实你每一个领域"
    },
    {
      "start": 363.68,
      "end": 364.52,
      "text": "你是有上限的"
    },
    {
      "start": 364.52,
      "end": 365.72,
      "text": "天后版是一肯立偶的"
    },
    {
      "start": 365.72,
      "end": 366.36,
      "text": "你做大以后"
    },
    {
      "start": 366.36,
      "end": 367.8,
      "text": "是不是你就开始向上整合"
    },
    {
      "start": 367.8,
      "end": 368.32,
      "text": "向下整合"
    },
    {
      "start": 368.32,
      "end": 368.92,
      "text": "对吧"
    },
    {
      "start": 368.92,
      "end": 369.76,
      "text": "你说郭摩坏了"
    },
    {
      "start": 369.76,
      "end": 370.84,
      "text": "你是要去整合下类传"
    },
    {
      "start": 370.84,
      "end": 372.44,
      "text": "你是无限整合下税是吧"
    },
    {
      "start": 372.44,
      "end": 373.52,
      "text": "那你就在不红高"
    },
    {
      "start": 373.52,
      "end": 374.72,
      "text": "20基基地每个公司是吧"
    },
    {
      "start": 374.72,
      "end": 375.56,
      "text": "让你整合完了"
    },
    {
      "start": 375.56,
      "end": 376.24,
      "text": "可不可能吗"
    },
    {
      "start": 376.24,
      "end": 377.04,
      "text": "就是你"
    },
    {
      "start": 377.04,
      "end": 378.4,
      "text": "研发创新的权"
    },
    {
      "start": 378.4,
      "end": 379.92,
      "text": "扩产的钱是不缺的"
    },
    {
      "start": 379.92,
      "end": 381.6,
      "text": "但是你不要搞出几百亿"
    },
    {
      "start": 381.6,
      "end": 382.32,
      "text": "在里面理财了"
    },
    {
      "start": 383.24,
      "end": 383.6,
      "text": "第五个"
    },
    {
      "start": 383.6,
      "end": 384.16,
      "text": "三个月了"
    },
    {
      "start": 384.16,
      "end": 385.04,
      "text": "这个夜轮的龙头"
    },
    {
      "start": 385.04,
      "end": 385.72,
      "text": "这个克克"
    },
    {
      "start": 385.72,
      "end": 386.68,
      "text": "就是夜轮版"
    },
    {
      "start": 386.68,
      "end": 387.2,
      "text": "DDO"
    },
    {
      "start": 387.2,
      "end": 387.8,
      "text": "还有这个什么"
    },
    {
      "start": 387.8,
      "end": 388.68,
      "text": "轮版是曾经是"
    },
    {
      "start": 388.68,
      "end": 389.56,
      "text": "几番空调精密"
    },
    {
      "start": 389.56,
      "end": 391.0,
      "text": "那全球的有这个绿购"
    },
    {
      "start": 391.0,
      "end": 391.8,
      "text": "那么风险去代表"
    },
    {
      "start": 391.8,
      "end": 392.92,
      "text": "这些戏的咱们就摆着念了"
    },
    {
      "start": 392.92,
      "end": 393.32,
      "text": "然后呢"
    },
    {
      "start": 393.32,
      "end": 394.72,
      "text": "夜轮42025年"
    },
    {
      "start": 394.72,
      "end": 395.48,
      "text": "是34亿"
    },
    {
      "start": 395.48,
      "end": 397.16,
      "text": "每到28年是136亿"
    },
    {
      "start": 397.16,
      "end": 398.2,
      "text": "这空间抢上了"
    },
    {
      "start": 398.2,
      "end": 399.56,
      "text": "也肯定没有纯粗的萌萌"
    },
    {
      "start": 399.56,
      "end": 401.0,
      "text": "因为他没有缺了这个程度"
    },
    {
      "start": 401.0,
      "end": 401.8,
      "text": "夜轮只是说"
    },
    {
      "start": 401.8,
      "end": 402.84,
      "text": "因为新一代的"
    },
    {
      "start": 402.84,
      "end": 404.48,
      "text": "因为达着这个机会出现以后"
    },
    {
      "start": 404.48,
      "end": 405.6,
      "text": "他就是只有夜轮"
    },
    {
      "start": 405.6,
      "end": 406.12,
      "text": "还算得了"
    },
    {
      "start": 406.12,
      "end": 406.84,
      "text": "算得住了"
    },
    {
      "start": 406.84,
      "end": 408.44,
      "text": "就爆发点就空气冷却到几线了"
    },
    {
      "start": 408.44,
      "end": 409.64,
      "text": "夜轮成为服务器新标配"
    },
    {
      "start": 409.64,
      "end": 411.16,
      "text": "那么就是下一代的露饼狗价"
    },
    {
      "start": 411.16,
      "end": 411.72,
      "text": "乌丹克威尔"
    },
    {
      "start": 411.72,
      "end": 412.76,
      "text": "这些东西就需要了"
    },
    {
      "start": 412.76,
      "end": 413.48,
      "text": "第六个"
    },
    {
      "start": 413.48,
      "end": 414.48,
      "text": "电源与配电"
    },
    {
      "start": 414.48,
      "end": 415.96,
      "text": "LPS比较高压子流"
    },
    {
      "start": 415.96,
      "end": 417.08,
      "text": "PDO还有编辑"
    },
    {
      "start": 417.08,
      "end": 418.2,
      "text": "就是这些血液工与传"
    },
    {
      "start": 418.2,
      "end": 419.8,
      "text": "核心那种就是高压子流供电"
    },
    {
      "start": 419.8,
      "end": 421.32,
      "text": "这个东西就是AI的那个"
    },
    {
      "start": 421.32,
      "end": 421.68,
      "text": "DWA"
    },
    {
      "start": 421.68,
      "end": 422.16,
      "text": "对不对"
    },
    {
      "start": 422.16,
      "end": 423.32,
      "text": "还有这个规感片"
    },
    {
      "start": 423.32,
      "end": 424.52,
      "text": "淡化大功率的旗舰"
    },
    {
      "start": 424.52,
      "end": 425.28,
      "text": "才发现出现"
    },
    {
      "start": 425.28,
      "end": 425.6,
      "text": "是吧"
    },
    {
      "start": 425.6,
      "end": 426.44,
      "text": "全球龙头这些"
    },
    {
      "start": 426.44,
      "end": 427.84,
      "text": "然后风险运代表这些东西"
    },
    {
      "start": 427.84,
      "end": 428.8,
      "text": "然后市场需求就是"
    },
    {
      "start": 428.8,
      "end": 431.6,
      "text": "数据中心电源市场2026年是数版一规模"
    },
    {
      "start": 431.6,
      "end": 434.0,
      "text": "风险运的全球电RG规模是60%出口"
    },
    {
      "start": 434.0,
      "end": 435.84,
      "text": "应AI需求7%36%"
    },
    {
      "start": 435.84,
      "end": 436.92,
      "text": "我说就是这些公司的"
    },
    {
      "start": 436.92,
      "end": 437.64,
      "text": "电RG的产能力"
    },
    {
      "start": 437.64,
      "end": 438.88,
      "text": "你排到2028年了"
    },
    {
      "start": 438.88,
      "end": 439.44,
      "text": "满了"
    },
    {
      "start": 439.44,
      "end": 441.44,
      "text": "因为单数据中心的通电需要一个小城市"
    },
    {
      "start": 441.44,
      "end": 442.44,
      "text": "然后这个东西其实"
    },
    {
      "start": 442.44,
      "end": 443.08,
      "text": "你可要看风险运"
    },
    {
      "start": 443.08,
      "end": 444.12,
      "text": "风险运的电网"
    },
    {
      "start": 444.12,
      "end": 445.32,
      "text": "那个国电就把做好了"
    },
    {
      "start": 445.32,
      "end": 446.32,
      "text": "主角是老外"
    },
    {
      "start": 446.32,
      "end": 447.24,
      "text": "因为老外是"
    },
    {
      "start": 447.24,
      "end": 448.44,
      "text": "让他自己做嘛"
    },
    {
      "start": 448.44,
      "end": 450.24,
      "text": "就说AI的电源的话"
    },
    {
      "start": 450.24,
      "end": 451.36,
      "text": "他除了电RG以外"
    },
    {
      "start": 451.36,
      "end": 452.2,
      "text": "还有个点是什么"
    },
    {
      "start": 452.2,
      "end": 454.2,
      "text": "就是AI数据中心的那个"
    },
    {
      "start": 454.2,
      "end": 454.84,
      "text": "持标楼"
    },
    {
      "start": 454.84,
      "end": 455.52,
      "text": "就是这个"
    },
    {
      "start": 455.52,
      "end": 456.76,
      "text": "我这位825%可以有"
    },
    {
      "start": 456.8,
      "end": 457.52,
      "text": "然后呢"
    },
    {
      "start": 457.52,
      "end": 458.12,
      "text": "就机贵"
    },
    {
      "start": 458.12,
      "end": 459.24,
      "text": "我看那么多颜报"
    },
    {
      "start": 459.24,
      "end": 460.92,
      "text": "机贵的含金量没有那么高"
    },
    {
      "start": 460.92,
      "end": 461.48,
      "text": "这这么说"
    },
    {
      "start": 461.48,
      "end": 462.52,
      "text": "现在的类传"
    },
    {
      "start": 462.52,
      "end": 464.28,
      "text": "就有二上去年的6030"
    },
    {
      "start": 464.28,
      "end": 465.28,
      "text": "可能就第一周吧"
    },
    {
      "start": 465.28,
      "end": 465.84,
      "text": "或者第二周"
    },
    {
      "start": 465.84,
      "end": 466.8,
      "text": "你们懂那个感觉是吧"
    },
    {
      "start": 466.8,
      "end": 467.72,
      "text": "那三大货战"
    },
    {
      "start": 467.72,
      "end": 469.04,
      "text": "环节就是数据中心建设"
    },
    {
      "start": 469.04,
      "end": 469.76,
      "text": "IDC愿意"
    },
    {
      "start": 469.76,
      "end": 470.92,
      "text": "那么这东西是模块"
    },
    {
      "start": 470.92,
      "end": 471.52,
      "text": "机房机贵"
    },
    {
      "start": 471.52,
      "end": 472.32,
      "text": "东书需算数据"
    },
    {
      "start": 472.32,
      "end": 472.76,
      "text": "老外呢"
    },
    {
      "start": 472.76,
      "end": 473.48,
      "text": "就是这个略过"
    },
    {
      "start": 473.48,
      "end": 474.2,
      "text": "那风险运呢"
    },
    {
      "start": 474.2,
      "end": 474.96,
      "text": "跳过那么"
    },
    {
      "start": 474.96,
      "end": 475.6,
      "text": "淺烈"
    },
    {
      "start": 475.6,
      "end": 477.12,
      "text": "风险运算的东西市场28年"
    },
    {
      "start": 477.12,
      "end": 478.0,
      "text": "超2800亿"
    },
    {
      "start": 478.0,
      "end": 478.68,
      "text": "绿色几月化"
    },
    {
      "start": 478.68,
      "end": 479.56,
      "text": "那么26年"
    },
    {
      "start": 479.56,
      "end": 480.8,
      "text": "AI专业我IDC就是"
    },
    {
      "start": 480.8,
      "end": 481.64,
      "text": "业冷家高"
    },
    {
      "start": 481.64,
      "end": 482.84,
      "text": "终于异度方量"
    },
    {
      "start": 482.84,
      "end": 484.4,
      "text": "这个先给个9.5吧"
    },
    {
      "start": 484.4,
      "end": 485.28,
      "text": "就他就是"
    },
    {
      "start": 485.28,
      "end": 486.28,
      "text": "比如内裙拆头"
    },
    {
      "start": 486.28,
      "end": 487.24,
      "text": "我认为就是拆头"
    },
    {
      "start": 487.24,
      "end": 488.48,
      "text": "或者说就等量的"
    },
    {
      "start": 488.48,
      "end": 489.8,
      "text": "这个就新时代的开放来了"
    },
    {
      "start": 489.8,
      "end": 491.0,
      "text": "新基建的总歌"
    },
    {
      "start": 491.0,
      "end": 492.48,
      "text": "那么这个春节"
    },
    {
      "start": 492.48,
      "end": 494.36,
      "text": "最大塌是方的数据是"
    },
    {
      "start": 494.36,
      "end": 495.32,
      "text": "把我们新时代的哪个呢"
    },
    {
      "start": 495.32,
      "end": 496.36,
      "text": "谁弹是12.0"
    },
    {
      "start": 496.36,
      "end": 497.72,
      "text": "谁弹是12.0是哪家的"
    },
    {
      "start": 497.72,
      "end": 499.24,
      "text": "他的数据中心就谁弹见"
    },
    {
      "start": 499.8,
      "end": 500.24,
      "text": "说了嘛"
    },
    {
      "start": 500.24,
      "end": 500.88,
      "text": "对不对"
    },
    {
      "start": 500.88,
      "end": 501.36,
      "text": "第八个"
    },
    {
      "start": 501.36,
      "end": 503.36,
      "text": "电力基础设施与绿色人员"
    },
    {
      "start": 503.36,
      "end": 503.8,
      "text": "这个呢"
    },
    {
      "start": 503.8,
      "end": 505.0,
      "text": "我认为就是现在"
    },
    {
      "start": 505.0,
      "end": 506.48,
      "text": "他不是从不头前"
    },
    {
      "start": 506.48,
      "end": 508.44,
      "text": "他是于一个超长期"
    },
    {
      "start": 508.44,
      "end": 510.32,
      "text": "比如说他是坐在五年计划里面的"
    },
    {
      "start": 510.32,
      "end": 511.68,
      "text": "就该发挥的时候也发挥了"
    },
    {
      "start": 511.68,
      "end": 513.4,
      "text": "这风险军的人量肯定是浓于的"
    },
    {
      "start": 513.4,
      "end": 513.92,
      "text": "你干嘛"
    },
    {
      "start": 513.92,
      "end": 515.4,
      "text": "数据中心号顶2023年"
    },
    {
      "start": 515.4,
      "end": 516.84,
      "text": "全球四到五倍的增长"
    },
    {
      "start": 516.84,
      "end": 518.04,
      "text": "风险军的西衣布绿色"
    },
    {
      "start": 518.04,
      "end": 518.84,
      "text": "蒜里的基地"
    },
    {
      "start": 518.84,
      "end": 521.0,
      "text": "这种军风冷光轮水电"
    },
    {
      "start": 521.0,
      "end": 521.6,
      "text": "都在弄"
    },
    {
      "start": 521.6,
      "end": 523.76,
      "text": "去年两家那些东西都在转了"
    },
    {
      "start": 523.76,
      "end": 525.24,
      "text": "你说把这些里面"
    },
    {
      "start": 525.24,
      "end": 526.56,
      "text": "如果要看去看海外也有"
    },
    {
      "start": 526.56,
      "end": 528.52,
      "text": "就海外的定单能直接推升"
    },
    {
      "start": 528.52,
      "end": 529.16,
      "text": "内部的话"
    },
    {
      "start": 529.16,
      "end": 530.12,
      "text": "该排的都排了"
    },
    {
      "start": 530.12,
      "end": 531.12,
      "text": "早就坐在前面了"
    },
    {
      "start": 531.12,
      "end": 532.88,
      "text": "第九个就是软电平台与蒜里的要度"
    },
    {
      "start": 532.88,
      "end": 533.56,
      "text": "这就是各种云"
    },
    {
      "start": 533.56,
      "end": 534.36,
      "text": "这个呢就不用说了"
    },
    {
      "start": 534.36,
      "end": 534.96,
      "text": "就是说你看"
    },
    {
      "start": 534.96,
      "end": 536.84,
      "text": "整体潜力和爆发点学习入境"
    },
    {
      "start": 536.84,
      "end": 537.52,
      "text": "全局潜力"
    },
    {
      "start": 537.52,
      "end": 538.64,
      "text": "二六年全球的ART"
    },
    {
      "start": 538.64,
      "end": 539.84,
      "text": "主说是投资或差两千亿"
    },
    {
      "start": 539.84,
      "end": 540.6,
      "text": "每刀"
    },
    {
      "start": 540.6,
      "end": 541.76,
      "text": "这个东西有之后性"
    },
    {
      "start": 541.76,
      "end": 543.24,
      "text": "光老美那个七千元"
    },
    {
      "start": 543.24,
      "end": 544.52,
      "text": "说到投六千五百亿美金"
    },
    {
      "start": 544.52,
      "end": 545.88,
      "text": "那就是四万多亿红票质"
    },
    {
      "start": 545.88,
      "end": 547.24,
      "text": "专业军的蒜里规模产业"
    },
    {
      "start": 547.24,
      "end": 547.96,
      "text": "是1.2万亿"
    },
    {
      "start": 547.96,
      "end": 549.08,
      "text": "风险军的优势什么"
    },
    {
      "start": 549.08,
      "end": 551.56,
      "text": "就是那样大 管保 便宜 新加平高"
    },
    {
      "start": 551.56,
      "end": 552.72,
      "text": "你要说单兵坐在那里"
    },
    {
      "start": 552.72,
      "end": 553.56,
      "text": "有没有那么强没有"
    },
    {
      "start": 553.56,
      "end": 555.84,
      "text": "风险军现在没有说能达到H200"
    },
    {
      "start": 555.84,
      "end": 556.6,
      "text": "这种显卡"
    },
    {
      "start": 556.6,
      "end": 557.64,
      "text": "这种蒜里的这种芯片"
    },
    {
      "start": 557.64,
      "end": 558.6,
      "text": "单片没有"
    },
    {
      "start": 558.6,
      "end": 560.6,
      "text": "但是我可以糊涂挖 七个打一个嘛"
    },
    {
      "start": 560.6,
      "end": 562.0,
      "text": "所以说这个节点"
    },
    {
      "start": 562.0,
      "end": 564.0,
      "text": "你看2026到2028爆发点会中"
    },
    {
      "start": 564.0,
      "end": 565.28,
      "text": "上半年就是不来科威"
    },
    {
      "start": 565.28,
      "end": 566.68,
      "text": "要交付才万卡进行落地"
    },
    {
      "start": 566.68,
      "end": 568.08,
      "text": "伏级网络光萌化业了"
    },
    {
      "start": 568.08,
      "end": 568.92,
      "text": "订单报征"
    },
    {
      "start": 568.92,
      "end": 571.08,
      "text": "就是伏伏器是谁下定的"
    },
    {
      "start": 571.08,
      "end": 572.48,
      "text": "就比如说我现在公司"
    },
    {
      "start": 572.48,
      "end": 573.48,
      "text": "多来了五千个人"
    },
    {
      "start": 573.48,
      "end": 575.0,
      "text": "我要给他们配合去先到房子"
    },
    {
      "start": 575.0,
      "end": 576.76,
      "text": "那是不是我会把这个任务交给"
    },
    {
      "start": 576.76,
      "end": 577.76,
      "text": "开发上去做"
    },
    {
      "start": 577.76,
      "end": 578.96,
      "text": "开发上再给我说"
    },
    {
      "start": 578.96,
      "end": 579.76,
      "text": "你需要达到多少算力"
    },
    {
      "start": 579.76,
      "end": 581.36,
      "text": "你需要配置多少的类传"
    },
    {
      "start": 581.36,
      "end": 582.48,
      "text": "GPU 光萌库尔"
    },
    {
      "start": 582.48,
      "end": 583.0,
      "text": "光炉游"
    },
    {
      "start": 583.0,
      "end": 584.16,
      "text": "你要怎么配对不对"
    },
    {
      "start": 584.16,
      "end": 586.16,
      "text": "就说你说我数据中心的建筑商"
    },
    {
      "start": 586.16,
      "end": 587.48,
      "text": "就说我上去采购多少算力"
    },
    {
      "start": 587.48,
      "end": 589.88,
      "text": "至于说怎么去实现最大的消负身体的事"
    },
    {
      "start": 589.88,
      "end": 590.24,
      "text": "对不对"
    },
    {
      "start": 590.24,
      "end": 591.44,
      "text": "我比较需要五百套房子"
    },
    {
      "start": 591.44,
      "end": 593.2,
      "text": "每套是一百四三品的套势"
    },
    {
      "start": 593.2,
      "end": 595.12,
      "text": "有电梯 乌光厅 两地两货"
    },
    {
      "start": 595.12,
      "end": 596.16,
      "text": "至于说怎么去画图"
    },
    {
      "start": 596.16,
      "end": 597.56,
      "text": "怎么去设计 怎么去买电源"
    },
    {
      "start": 597.56,
      "end": 598.44,
      "text": "买水泥 买钢琴"
    },
    {
      "start": 598.44,
      "end": 599.32,
      "text": "那就算你这个"
    },
    {
      "start": 599.32,
      "end": 600.16,
      "text": "开发上的事情了"
    },
    {
      "start": 600.16,
      "end": 600.76,
      "text": "谁"
    },
    {
      "start": 600.76,
      "end": 601.52,
      "text": "对不对"
    },
    {
      "start": 601.52,
      "end": 602.84,
      "text": "就是说需求的算力端"
    },
    {
      "start": 602.84,
      "end": 603.92,
      "text": "我要上去采购算力对不对"
    },
    {
      "start": 603.92,
      "end": 605.08,
      "text": "我给你多少钱就活动"
    },
    {
      "start": 605.08,
      "end": 606.4,
      "text": "其实我回家也就是说"
    },
    {
      "start": 606.4,
      "end": 608.08,
      "text": "我们实际上可以拔着这个"
    },
    {
      "start": 608.08,
      "end": 609.44,
      "text": "轮身视频这个类型的"
    },
    {
      "start": 609.44,
      "end": 610.12,
      "text": "27年了"
    },
    {
      "start": 610.12,
      "end": 611.36,
      "text": "如果中间有特别强的"
    },
    {
      "start": 611.36,
      "end": 612.36,
      "text": "咱们才说的"
    },
    {
      "start": 612.36,
      "end": 614.6,
      "text": "但目前我看不到确定更强的"
    },
    {
      "start": 614.6,
      "end": 616.52,
      "text": "因为外资也想来分蛋糕"
    },
    {
      "start": 616.52,
      "end": 618.76,
      "text": "你们是不知道这个春节期的多么抽象"
    },
    {
      "start": 618.76,
      "end": 620.6,
      "text": "自从内部把他们冲头房以后"
    },
    {
      "start": 620.6,
      "end": 622.4,
      "text": "很多老闆开始学汗语了"
    },
    {
      "start": 622.4,
      "end": 624.52,
      "text": "他们说我不是想学汗语"
    },
    {
      "start": 624.52,
      "end": 626.48,
      "text": "我只是想占了营的那边"
    },
    {
      "start": 626.48,
      "end": 627.88,
      "text": "这话就各自外了吧"
    },
    {
      "start": 627.88,
      "end": 629.4,
      "text": "就我不需要说什么"
    },
    {
      "start": 629.4,
      "end": 631.16,
      "text": "我去帮着谁 加入谁 帮着谁打赢"
    },
    {
      "start": 631.16,
      "end": 632.68,
      "text": "谁赢到我帮谁"
    },
    {
      "start": 632.68,
      "end": 633.52,
      "text": "真的就是这样子"
    },
    {
      "start": 633.52,
      "end": 634.92,
      "text": "非得含定量还在提升"
    },
    {
      "start": 634.92,
      "end": 636.08,
      "text": "你够说皇室当死了"
    },
    {
      "start": 636.08,
      "end": 637.56,
      "text": "我才会去赔你空雕楼的"
    },
    {
      "start": 637.56,
      "end": 638.6,
      "text": "皇室当活着的时候"
    },
    {
      "start": 638.6,
      "end": 639.8,
      "text": "你让我去我肯定不去"
    },
    {
      "start": 639.8,
      "end": 642.0,
      "text": "所以说 你看 中期就26年下半年到27年"
    },
    {
      "start": 642.0,
      "end": 642.8,
      "text": "推理规模化"
    },
    {
      "start": 642.8,
      "end": 645.04,
      "text": "其实现在可能已经在这个爆发的阶段了"
    },
    {
      "start": 645.04,
      "end": 646.76,
      "text": "春节习上班赶紧去看到了"
    },
    {
      "start": 646.76,
      "end": 648.28,
      "text": "对吧 电力平静这东西"
    },
    {
      "start": 648.28,
      "end": 650.0,
      "text": "这个是风险镜子来解决问题"
    },
    {
      "start": 650.0,
      "end": 652.2,
      "text": "这个东西你可以看它是一个怎么说呢"
    },
    {
      "start": 652.2,
      "end": 653.48,
      "text": "我不能说它是防御性板块"
    },
    {
      "start": 653.48,
      "end": 656.32,
      "text": "但它的爆发肯定没有说有情绪的强度"
    },
    {
      "start": 656.32,
      "end": 658.0,
      "text": "长期算力就是偷渴了 对不对"
    },
    {
      "start": 658.0,
      "end": 660.48,
      "text": "我们去年11月的视频里面就唱想过"
    },
    {
      "start": 660.48,
      "end": 661.84,
      "text": "没想到今年才二月"
    },
    {
      "start": 661.84,
      "end": 663.08,
      "text": "就因为大博星突破"
    },
    {
      "start": 663.08,
      "end": 663.92,
      "text": "以爆爆发"
    },
    {
      "start": 663.92,
      "end": 665.6,
      "text": "实现了电力变算力出口了"
    },
    {
      "start": 665.6,
      "end": 666.88,
      "text": "真是可惜可和"
    },
    {
      "start": 666.88,
      "end": 668.64,
      "text": "那也祝贺相信风险镜的家人"
    },
    {
      "start": 668.64,
      "end": 671.48,
      "text": "吃肉了 风险镜终于把电力变算力出口了"
    },
    {
      "start": 671.48,
      "end": 672.96,
      "text": "风险的质材没有什么质材的"
    },
    {
      "start": 672.96,
      "end": 674.0,
      "text": "毛美都解决不了"
    },
    {
      "start": 674.0,
      "end": 675.6,
      "text": "那么学习陆经济咱们就不说了什么"
    },
    {
      "start": 675.6,
      "end": 677.6,
      "text": "这个就七八十的铺盖完了"
    },
    {
      "start": 677.6,
      "end": 680.04,
      "text": "我就结合我看着了所有颜暴"
    },
    {
      "start": 680.04,
      "end": 681.0,
      "text": "再给大家讲一遍"
    }
  ]
}