{
  "language": "zh",
  "duration": 310.566875,
  "segments": [
    {
      "start": 0.59,
      "end": 3.39,
      "text": "大家好,今天給大家分享一個非常火的倉庫"
    },
    {
      "start": 3.39,
      "end": 4.79,
      "text": "叫Tradeen Agents"
    },
    {
      "start": 4.79,
      "end": 7.27,
      "text": "它在投眼領域目前是排第1"
    },
    {
      "start": 7.27,
      "end": 8.79,
      "text": "而且增速非常的快"
    },
    {
      "start": 8.79,
      "end": 10.79,
      "text": "已經拿了65K的薩"
    },
    {
      "start": 10.79,
      "end": 14.79,
      "text": "它一共給配置了12個A卷的投眼團隊"
    },
    {
      "start": 14.79,
      "end": 16.79,
      "text": "讓你進行投資的分析"
    },
    {
      "start": 16.79,
      "end": 17.79,
      "text": "然後開始之前"
    },
    {
      "start": 17.79,
      "end": 18.79,
      "text": "我再說一下"
    },
    {
      "start": 18.79,
      "end": 20.79,
      "text": "本期只拆解開源的項目加購"
    },
    {
      "start": 20.79,
      "end": 22.79,
      "text": "不夠成任何的建議"
    },
    {
      "start": 22.79,
      "end": 27.9,
      "text": "為什麼要用這個12個A卷的投眼團隊"
    },
    {
      "start": 27.9,
      "end": 30.3,
      "text": "因為單A卷它只有一個分析式"
    },
    {
      "start": 30.3,
      "end": 31.5,
      "text": "數據進,結論出"
    },
    {
      "start": 31.5,
      "end": 33.1,
      "text": "沒有對抗沒有質疑這個產出"
    },
    {
      "start": 33.1,
      "end": 35.1,
      "text": "其實你不知道它的質量好壞的"
    },
    {
      "start": 35.1,
      "end": 37.1,
      "text": "如果你配備了12個A卷的話"
    },
    {
      "start": 37.1,
      "end": 37.9,
      "text": "它有分析的"
    },
    {
      "start": 37.9,
      "end": 38.7,
      "text": "有辨論的"
    },
    {
      "start": 38.7,
      "end": 39.5,
      "text": "有裁判的"
    },
    {
      "start": 39.5,
      "end": 40.1,
      "text": "有封控的"
    },
    {
      "start": 40.1,
      "end": 41.7,
      "text": "最後還有拍板的"
    },
    {
      "start": 41.7,
      "end": 43.7,
      "text": "這個真的是看多跟看空"
    },
    {
      "start": 43.7,
      "end": 47.7,
      "text": "真刀真槍的在互相去辨論"
    },
    {
      "start": 47.7,
      "end": 49.3,
      "text": "這個整套的Tradeen Agents"
    },
    {
      "start": 49.3,
      "end": 50.1,
      "text": "它有5層的流水"
    },
    {
      "start": 50.1,
      "end": 51.7,
      "text": "首先第一層是信息的採集"
    },
    {
      "start": 51.7,
      "end": 53.2,
      "text": "它有4個分析式"
    },
    {
      "start": 53.2,
      "end": 55.3,
      "text": "技術分析與請新聞基本面"
    },
    {
      "start": 55.3,
      "end": 58.3,
      "text": "它據通過API來拉這個數據"
    },
    {
      "start": 58.3,
      "end": 59.9,
      "text": "然後第二層是多空的辨論"
    },
    {
      "start": 59.9,
      "end": 61.3,
      "text": "根據這4分報告"
    },
    {
      "start": 61.3,
      "end": 64.1,
      "text": "多頭空頭分別"
    },
    {
      "start": 64.1,
      "end": 65.9,
      "text": "出據它們的觀點"
    },
    {
      "start": 65.9,
      "end": 67.7,
      "text": "然後第三輪是裁判的判定"
    },
    {
      "start": 67.7,
      "end": 70.9,
      "text": "它讀完多頭跟空頭的辨論記錄之後"
    },
    {
      "start": 70.9,
      "end": 72.3,
      "text": "判定是一個有說服力"
    },
    {
      "start": 72.3,
      "end": 74.7,
      "text": "然後輸出無黨的評級"
    },
    {
      "start": 74.7,
      "end": 76.5,
      "text": "第4輪是風險委員會"
    },
    {
      "start": 76.5,
      "end": 78.1,
      "text": "這個也是投眼公司的一些標配"
    },
    {
      "start": 78.1,
      "end": 81.5,
      "text": "然後它進行基金派、保守派、中心派"
    },
    {
      "start": 81.5,
      "end": 83.3,
      "text": "三方再也再吵一輪"
    },
    {
      "start": 83.3,
      "end": 85.1,
      "text": "最後就是Boss"
    },
    {
      "start": 85.1,
      "end": 87.1,
      "text": "根據所有的這些信息"
    },
    {
      "start": 87.1,
      "end": 88.3,
      "text": "跟歷史的記憶"
    },
    {
      "start": 88.3,
      "end": 89.9,
      "text": "然後形成最終一個結論"
    },
    {
      "start": 89.9,
      "end": 93.97,
      "text": "然後你的分析的結論就出來了"
    },
    {
      "start": 93.97,
      "end": 95.57,
      "text": "然後我從每個層級"
    },
    {
      "start": 95.57,
      "end": 97.37,
      "text": "跟大家在詳細拆解一下"
    },
    {
      "start": 97.37,
      "end": 98.17,
      "text": "首先第一個的"
    },
    {
      "start": 98.17,
      "end": 99.57,
      "text": "它是第一層是四個分析式"
    },
    {
      "start": 99.57,
      "end": 101.57,
      "text": "然後它通過API的數據"
    },
    {
      "start": 101.57,
      "end": 104.57,
      "text": "去進行它自己頂域的調研"
    },
    {
      "start": 104.57,
      "end": 106.57,
      "text": "我分析的是這個Amazon"
    },
    {
      "start": 106.57,
      "end": 108.17,
      "text": "就是亞馬遜"
    },
    {
      "start": 108.17,
      "end": 109.17,
      "text": "然後它記住分析"
    },
    {
      "start": 109.17,
      "end": 110.77,
      "text": "它去調這些MACD的數據"
    },
    {
      "start": 110.77,
      "end": 113.17,
      "text": "然後雨晴它去抓一些新聞"
    },
    {
      "start": 113.17,
      "end": 114.17,
      "text": "但是我這次實測的"
    },
    {
      "start": 114.17,
      "end": 115.97,
      "text": "它返回的新聞是空的"
    },
    {
      "start": 115.97,
      "end": 116.97,
      "text": "雨晴是空的"
    },
    {
      "start": 116.97,
      "end": 117.77,
      "text": "然後新聞分析式"
    },
    {
      "start": 117.77,
      "end": 119.97,
      "text": "它就會去抓一些宏觀的新聞"
    },
    {
      "start": 119.97,
      "end": 120.77,
      "text": "相關的新聞"
    },
    {
      "start": 120.77,
      "end": 123.57,
      "text": "基本面分析就去分析它的財務數據"
    },
    {
      "start": 123.57,
      "end": 124.57,
      "text": "然後這四個分析式"
    },
    {
      "start": 124.57,
      "end": 127.17,
      "text": "就會出據四分報告"
    },
    {
      "start": 127.17,
      "end": 129.57,
      "text": "它的這個方向的報告"
    },
    {
      "start": 129.57,
      "end": 130.97,
      "text": "然後多空的對決"
    },
    {
      "start": 130.97,
      "end": 132.77,
      "text": "就是多頭"
    },
    {
      "start": 132.77,
      "end": 135.17,
      "text": "它看多的原因是什麼"
    },
    {
      "start": 135.17,
      "end": 137.17,
      "text": "它會給根據這個報告"
    },
    {
      "start": 137.17,
      "end": 139.17,
      "text": "分析出來看多的原因"
    },
    {
      "start": 139.17,
      "end": 141.37,
      "text": "然後空頭它會根據這些報告"
    },
    {
      "start": 141.37,
      "end": 143.57,
      "text": "跟這些信息結合分析出來"
    },
    {
      "start": 143.57,
      "end": 144.77,
      "text": "它看空的原因"
    },
    {
      "start": 144.77,
      "end": 146.37,
      "text": "然後再到第三個層級"
    },
    {
      "start": 146.37,
      "end": 147.77,
      "text": "就是風險委員會"
    },
    {
      "start": 147.77,
      "end": 148.57,
      "text": "風險委員會"
    },
    {
      "start": 148.57,
      "end": 151.17,
      "text": "就會進行一個討論"
    },
    {
      "start": 151.17,
      "end": 152.77,
      "text": "激進的保守的中性的"
    },
    {
      "start": 152.77,
      "end": 156.64,
      "text": "大家都會出各自的這個結論"
    },
    {
      "start": 156.64,
      "end": 158.24,
      "text": "然後最後就是這個總經理"
    },
    {
      "start": 158.24,
      "end": 160.04,
      "text": "根據這些結論進行的拍板"
    },
    {
      "start": 160.04,
      "end": 161.24,
      "text": "它會選擇裁那的觀點"
    },
    {
      "start": 161.24,
      "end": 162.44,
      "text": "你看它裁那的"
    },
    {
      "start": 162.44,
      "end": 163.24,
      "text": "左邊那個觀點"
    },
    {
      "start": 163.24,
      "end": 164.64,
      "text": "就是基本面很扎實"
    },
    {
      "start": 164.64,
      "end": 167.24,
      "text": "1556億的營收"
    },
    {
      "start": 167.24,
      "end": 168.24,
      "text": "1124"
    },
    {
      "start": 168.24,
      "end": 170.44,
      "text": "然後AS本雖然開出多"
    },
    {
      "start": 170.44,
      "end": 171.84,
      "text": "但是是長期的布局"
    },
    {
      "start": 171.84,
      "end": 173.44,
      "text": "然後這個是一個技術的"
    },
    {
      "start": 173.44,
      "end": 174.44,
      "text": "景氣的風險"
    },
    {
      "start": 174.44,
      "end": 175.64,
      "text": "這個就是關稅"
    },
    {
      "start": 175.64,
      "end": 177.44,
      "text": "類似之類的"
    },
    {
      "start": 177.44,
      "end": 178.24,
      "text": "它會綜合"
    },
    {
      "start": 178.24,
      "end": 179.64,
      "text": "然後最後給出了這個觀點"
    },
    {
      "start": 179.64,
      "end": 182.94,
      "text": "就是直觀"
    },
    {
      "start": 182.94,
      "end": 184.34,
      "text": "這個確定Agent"
    },
    {
      "start": 184.34,
      "end": 186.54,
      "text": "它有三個比較巧妙的設計"
    },
    {
      "start": 186.54,
      "end": 188.34,
      "text": "第一個是雙模型"
    },
    {
      "start": 188.34,
      "end": 190.34,
      "text": "它前10個的這個角色"
    },
    {
      "start": 190.34,
      "end": 192.14,
      "text": "是用便宜的模型"
    },
    {
      "start": 192.14,
      "end": 193.34,
      "text": "然後第二個"
    },
    {
      "start": 193.34,
      "end": 194.54,
      "text": "最後兩個拍板的模型"
    },
    {
      "start": 194.54,
      "end": 195.74,
      "text": "它是用貴的模型"
    },
    {
      "start": 195.74,
      "end": 196.94,
      "text": "相當於實習生"
    },
    {
      "start": 196.94,
      "end": 198.14,
      "text": "就收集信息"
    },
    {
      "start": 198.14,
      "end": 199.14,
      "text": "然後大概討論一下"
    },
    {
      "start": 199.14,
      "end": 199.94,
      "text": "然後最後老闆"
    },
    {
      "start": 199.94,
      "end": 201.74,
      "text": "通過這些信息來進行"
    },
    {
      "start": 201.74,
      "end": 202.74,
      "text": "最終的評判"
    },
    {
      "start": 202.74,
      "end": 204.14,
      "text": "評判會比較貴一點"
    },
    {
      "start": 204.14,
      "end": 206.34,
      "text": "第二個就記憶的反思"
    },
    {
      "start": 206.34,
      "end": 207.94,
      "text": "第一次它是角色蠢於Pending"
    },
    {
      "start": 207.94,
      "end": 209.94,
      "text": "第二次它就會拉真實的"
    },
    {
      "start": 209.94,
      "end": 210.94,
      "text": "所以然後進行"
    },
    {
      "start": 210.94,
      "end": 212.94,
      "text": "然後再寫反思"
    },
    {
      "start": 212.94,
      "end": 214.94,
      "text": "然後第三個就是"
    },
    {
      "start": 214.94,
      "end": 216.94,
      "text": "三級的降級"
    },
    {
      "start": 216.94,
      "end": 222.08,
      "text": "它幾乎尖容的所有的M廠商"
    },
    {
      "start": 222.08,
      "end": 223.48,
      "text": "這個是我的一個"
    },
    {
      "start": 223.48,
      "end": 224.28,
      "text": "針對它這個模型"
    },
    {
      "start": 224.28,
      "end": 226.48,
      "text": "撤平之後的一個觀察"
    },
    {
      "start": 226.48,
      "end": 227.68,
      "text": "跟思考"
    },
    {
      "start": 227.68,
      "end": 229.68,
      "text": "我覺得它問題最大的"
    },
    {
      "start": 229.68,
      "end": 230.48,
      "text": "就在於它的"
    },
    {
      "start": 230.48,
      "end": 231.32,
      "text": "四個分析師"
    },
    {
      "start": 231.32,
      "end": 233.08,
      "text": "接著最便宜的模型"
    },
    {
      "start": 233.08,
      "end": 235.08,
      "text": "因為四個分析師"
    },
    {
      "start": 235.08,
      "end": 236.08,
      "text": "它是整一個"
    },
    {
      "start": 236.08,
      "end": 237.08,
      "text": "我們後面這幾個"
    },
    {
      "start": 237.08,
      "end": 240.08,
      "text": "辨論、裁判、風險、拍板的地積"
    },
    {
      "start": 240.08,
      "end": 241.08,
      "text": "但你地積"
    },
    {
      "start": 241.08,
      "end": 243.08,
      "text": "如果你的智量不行的話"
    },
    {
      "start": 243.08,
      "end": 244.08,
      "text": "就它調研的智量不行的話"
    },
    {
      "start": 244.08,
      "end": 245.08,
      "text": "那其實後面這些"
    },
    {
      "start": 245.08,
      "end": 246.08,
      "text": "其實都說白了"
    },
    {
      "start": 246.08,
      "end": 247.08,
      "text": "可能可能會白扯"
    },
    {
      "start": 247.08,
      "end": 248.08,
      "text": "因為信息不準確"
    },
    {
      "start": 248.08,
      "end": 250.08,
      "text": "所以我覺得這個模型"
    },
    {
      "start": 250.08,
      "end": 252.08,
      "text": "還是需要進行改善"
    },
    {
      "start": 252.08,
      "end": 254.08,
      "text": "就是需要把四個分析師"
    },
    {
      "start": 254.08,
      "end": 255.08,
      "text": "它抓取的數據"
    },
    {
      "start": 255.08,
      "end": 256.08,
      "text": "首先要貴的模型去抓取"
    },
    {
      "start": 256.08,
      "end": 257.08,
      "text": "它求完之後"
    },
    {
      "start": 257.08,
      "end": 259.08,
      "text": "要論證它抓取來的信息"
    },
    {
      "start": 259.08,
      "end": 260.08,
      "text": "準備準確"
    },
    {
      "start": 260.08,
      "end": 261.08,
      "text": "就是它這個報告準備準確"
    },
    {
      "start": 261.08,
      "end": 263.08,
      "text": "我覺得這個模塊需要在"
    },
    {
      "start": 263.08,
      "end": 264.08,
      "text": "复杂畫下來"
    },
    {
      "start": 264.08,
      "end": 265.08,
      "text": "然後再到辨論、再到裁判"
    },
    {
      "start": 265.08,
      "end": 268.08,
      "text": "這樣整個的信息才是更精準的"
    },
    {
      "start": 268.08,
      "end": 273.15,
      "text": "然後最後我再做一個小小的總結"
    },
    {
      "start": 273.15,
      "end": 274.15,
      "text": "就是這12個A卷"
    },
    {
      "start": 274.15,
      "end": 275.15,
      "text": "是真的在相互辨論的"
    },
    {
      "start": 275.15,
      "end": 277.15,
      "text": "所以這個確定A卷"
    },
    {
      "start": 277.15,
      "end": 279.15,
      "text": "這個庫非常火的原因就在這裡"
    },
    {
      "start": 279.15,
      "end": 280.15,
      "text": "然後它比單一卷的"
    },
    {
      "start": 280.15,
      "end": 281.15,
      "text": "肯定是更優秀的"
    },
    {
      "start": 281.15,
      "end": 283.15,
      "text": "單一卷會自作自畫"
    },
    {
      "start": 283.15,
      "end": 285.15,
      "text": "它比單一卷靠譜的很多"
    },
    {
      "start": 286.15,
      "end": 288.15,
      "text": "但它有的確線"
    },
    {
      "start": 288.15,
      "end": 291.15,
      "text": "後續會考慮進行改造改善"
    },
    {
      "start": 291.15,
      "end": 293.15,
      "text": "然後它這個多A卷的體系"
    },
    {
      "start": 293.15,
      "end": 294.15,
      "text": "這個確定A卷"
    },
    {
      "start": 294.15,
      "end": 295.15,
      "text": "它是沒有這個 UI 交互介面的"
    },
    {
      "start": 295.15,
      "end": 297.15,
      "text": "未來我也可以設計一個"
    },
    {
      "start": 297.15,
      "end": 299.15,
      "text": "交互的介面"
    },
    {
      "start": 299.15,
      "end": 301.15,
      "text": "然後再加上我的改造分享給大家"
    },
    {
      "start": 301.15,
      "end": 304.15,
      "text": "最後也歡迎大家收藏關注"
    },
    {
      "start": 304.15,
      "end": 306.15,
      "text": "期待我下一期的這個視頻"
    },
    {
      "start": 306.15,
      "end": 307.15,
      "text": "謝謝大家"
    }
  ]
}